scheming_flask.py
scheming_flask-0.2.0.dist-info/METADATA
scheming_flask-0.2.0.dist-info/RECORD
scheming_flask-0.2.0.dist-info/WHEEL
scheming_flask-0.2.0.dist-info/top_level.txt
