Metadata-Version: 2.1
Name: scheming-flask
Version: 0.2.0
Summary: Use JSON Schema to validate incoming requests
Home-page: https://github.com/timmartin19/scheming-flask
Author: Tim Martin
Author-email: oss@timmartin.me
License: MIT license
Keywords: scheming_flask jsonschema flask
Platform: UNKNOWN
Classifier: Development Status :: 2 - Pre-Alpha
Classifier: Intended Audience :: Developers
Classifier: License :: OSI Approved :: MIT License
Classifier: Natural Language :: English
Classifier: Programming Language :: Python :: 2
Classifier: Programming Language :: Python :: 2.7
Classifier: Programming Language :: Python :: 3
Classifier: Programming Language :: Python :: 3.4
Classifier: Programming Language :: Python :: 3.5
Classifier: Programming Language :: Python :: 3.6
Requires-Dist: jsonschema
Requires-Dist: flask
